mylib1_048/__init__.py
mylib1_048-0.1.dist-info/LICENSE.txt
mylib1_048-0.1.dist-info/METADATA
mylib1_048-0.1.dist-info/WHEEL
mylib1_048-0.1.dist-info/top_level.txt
mylib1_048-0.1.dist-info/RECORD
