Metadata-Version: 2.1
Name: mylib1-048
Version: 0.1
Summary: for calculating square
Home-page: UNKNOWN
Author: Swaraj
Author-email: sontakkeswaraj04@gmail.com
License: UNKNOWN
Platform: UNKNOWN
Classifier: Programming Language :: Python :: 3
Classifier: License :: OSI Approved :: MIT License
Classifier: Operating System :: OS Independent
License-File: LICENSE.txt
